Workbook

Sheet Supuestos
A1: ANÁLISIS FINANCIERO — PROYECTO GAMMA
A2: Corporación Multi Inversiones · Mandante 402 · Unidad de Energía
A3: ⬛ Celdas en AZUL sobre AMARILLO = editables | Resto = calculado automáticamente
A5: 1. INGRESOS DEL GESTOR (modificar aquí)
A6: Salario ordinario mensual (bruto) | B6: 11000 | D6: Salario de mercado — punto medio del rango real para Analista/Gestor de Datos Maestros en empresas guatemaltecas (Q9,000–Q13,000), validado contra promedio de mercado Computrabajo GT
A7: Bonificación incentivo mensual (fija) | B7: 250 | D7: Bonificación Incentivo obligatoria — Decreto 78-89, Código de Trabajo de Guatemala (monto fijo legal, todos los trabajadores del sector privado)
A8: TOTAL INGRESOS BRUTOS MENSUALES | B8: =B6+B7 -> 11250 | D8: Salario + Bonificacion
A10: 2. CARGAS PATRONALES (fijas por ley — no editar)
A11: IGSS patronal | B11: 0.1267 | C11: =B8*B11 -> 1425.375 | D11: Acuerdo 1308 IGSS Guatemala
A12: Bono 14 (prorrateo mensual) | B12: 0.0833 | C12: =B8*B12 -> 937.125 | D12: 1 salario anual ÷ 12 meses · Decreto 42-92
A13: Aguinaldo (prorrateo mensual) | B13: 0.0833 | C13: =B8*B13 -> 937.125 | D13: 1 salario anual ÷ 12 meses · Código de Trabajo
A14: Vacaciones (prorrateo mensual) | B14: 0.0575 | C14: =B8*B14 -> 646.875 | D14: 15 días hábiles ÷ 261 días laborales anuales
A15: FACTOR TOTAL CARGAS PATRONALES | B15: =1+B11+B12+B13+B14 -> 1.3508 | C15: =B8*(B11+B12+B13+B14) -> 3946.5 | D15: 135.08% del salario bruto
A16: COSTO TOTAL MENSUAL PARA CMI | B16: =B8*B15 -> 15196.5 | C16: =B8+C15 -> 15196.5 | D16: Ingresos brutos + cargas patronales
A18: 3. HORAS LABORABLES Y COSTO-HORA
A19: Semanas laborables al año | B19: 52 | D19: Año calendario
A20: Días laborables por semana | B20: 5 | D20: Lunes a viernes
A21: Horas por día | B21: 8 | D21: Jornada ordinaria
A22: Días laborables al año | B22: 261 | D22: Referencia Guatemala 2026
A23: Horas laborables por mes | B23: =(B19*B20*B21)/12 -> 173.33333 | D23: (52 semanas × 5 días × 8 hrs) ÷ 12
A24: COSTO HORA-GESTOR PARA CMI | B24: =C16/B23 -> 87.672115 | D24: Este es el número clave para el análisis de ahorro
A26: 4. PARÁMETROS OPERATIVOS DEL M402
A27: Número de gestores de datos maestros | B27: 5 | D27: Dato real CMI — M402 ENE
A28: Tipo de cambio Q/USD (referencia) | B28: 7.75 | D28: Julio 2026
A30: 5. TIEMPOS DE GESTIÓN — DATOS REALES (Tablero CMI)
A31: Tiempo efectivo promedio PRE-GAMMA (hrs/sol.) | B31: 3.3437 | D31: 353 solicitudes · 16 feb – 16 jun 2026
A32: Tiempo efectivo mediana PRE-GAMMA (hrs/sol.) | B32: 2.8167 | D32: 353 solicitudes · 16 feb – 16 jun 2026
A33: Tiempo efectivo promedio POST-GAMMA (hrs/sol.) | B33: 1.4444 | D33: 84 solicitudes · 18 jun–18 jul 2026 (excl. 34 outliers en cola por vacaciones, 23 jun–1 jul)
A34: Tiempo efectivo mediana POST-GAMMA (hrs/sol.) | B34: 1.3083 | D34: 84 solicitudes · 18 jun–18 jul 2026 (excl. 34 outliers en cola por vacaciones, 23 jun–1 jul)
A35: Solicitudes reales 2025 (referencia anual) | B35: 2963 | D35: Dato real CMI 2025 — UEN Energía · Proceso Crear
A37: 6. TIEMPO PROCESO INICIO–FIN (ciclo completo — referencia complementaria, no usado en ROI)
A38: Tiempo proceso promedio PRE-GAMMA (hrs/sol.) | B38: 5.7551 | D38: 353 solicitudes · 16 feb–16 jun 2026
A39: Tiempo proceso promedio POST-GAMMA (hrs/sol.) | B39: 4.8063 | D39: 84 solicitudes · 18 jun–18 jul 2026 (excl. outliers vacaciones)
A40: Nota | D40: Incluye tiempo de cola/espera; no representa costo directo de gestor y por eso no alimenta el ROI
A42: 7. FUENTES DE DATOS DE MERCADO
A43: Salario base (B6): | D43: Punto medio del rango de mercado real (Q9,000–Q13,000) para roles de Analista/Gestor de Datos Maestros en Guatemala, validado profesionalmente. Ancla externa: Computrabajo GT, promedio Analista de Datos Q8,541/mes.
A44: Bonificación (B7): | D44: Decreto 78-89, Código de Trabajo de Guatemala — Bonificación Incentivo obligatoria, Q250/mes fijo para todo trabajador del sector privado.
A45: Referencia adicional consultada: | D45: Computrabajo Guatemala — "Salario de Analista de datos": promedio de mercado Q8,541/mes (182,693 fuentes, últimos 12 meses). https://gt.computrabajo.com/salarios/analista-de-datos

Sheet B1 - Ahorro Tiempo
A1: BENEFICIO 1 — REDUCCIÓN DEL TIEMPO DE GESTIÓN (Anual Recurrente)
A2: Basado en tiempos reales del Tablero CMI · Pre vs Post GAMMA
A4: Concepto | B4: Basado en Promedio | C4: Basado en Mediana | D4: Nota
A5: Tiempo efectivo PRE-GAMMA (hrs/solicitud) | B5: =Supuestos!B31 -> 3.3437 | C5: =Supuestos!B32 -> 2.8167 | D5: Promedio real PRE-GAMMA: 3.3437 hrs (n=353)
A6: Tiempo efectivo POST-GAMMA (hrs/solicitud) | B6: =Supuestos!B33 -> 1.4444 | C6: =Supuestos!B34 -> 1.3083 | D6: Promedio real POST-GAMMA: 1.4444 hrs (n=84)
A7: Reducción por solicitud (hrs) | B7: =B5-B6 -> 1.8993 | C7: =C5-C6 -> 1.5084 | D7: Reducción promedio: 1.8993 hrs · mediana: 1.5084 hrs
A8: Reducción porcentual | B8: =(B5-B6)/B5 -> 0.56802345 | C8: =(C5-C6)/C5 -> 0.53552029 | D8: Mayor = mejor mejora relativa
A9: Solicitudes anuales (referencia 2025) | B9: =Supuestos!B35 -> 2963 | C9: =Supuestos!B35 -> 2963 | D9: Actualizar con dato 2026 cuando esté disponible
A10: Total horas ahorradas al año | B10: =B7*B9 -> 5627.6259 | C10: =C7*C9 -> 4469.3892 | D10: Tiempo recuperado por el equipo gestor
A11: Costo hora-gestor CMI | B11: =Supuestos!B24 -> 87.672115 | C11: =Supuestos!B24 -> 87.672115 | D11: Vinculado a hoja Supuestos
A12: AHORRO ANUAL ESTIMADO (Q) | B12: =B10*B11 -> 493385.87 | C12: =C10*C11 -> 391840.81 | D12: Beneficio económico directo para CMI
A13: AHORRO ANUAL ESTIMADO (USD) | B13: =B12/Supuestos!B28 -> 63662.693 | C13: =C12/Supuestos!B28 -> 50560.104 | D13: Tipo de cambio referencial julio 2026

Sheet Costos del Proyecto
A1: COSTOS DEL PROYECTO GAMMA
A2: Stack 100% open source · Inversión mínima para CMI
A4: Rubro | B4: Descripción | C4: Costo unitario | D4: Cantidad | E4: Total
A5: Servidor VPS (pruebas y despliegue) | B5: Infraestructura — construcción, pruebas y puesta en productivo (jul–sep 2026) | C5: USD 32.9/mes | D5: 3 meses | E5: =32.9*7.82*3 -> 771.834
A6: Capacitación a gestores | B6: 2 hrs × 5 gestores | C6: =Supuestos!B24&"/hora" -> 87.6721153846154/hora | D6: 10 horas | E6: =Supuestos!B24*2*Supuestos!B27 -> 876.72115
A7: Stack tecnológico (Python, FastAPI, Vue 3, PostgreSQL 16, Docker) | B7: 100% open source | C7: Q 0 | D7: — | E7: 0
A8: Google Gemini API | B8: Free tier — volumen de prototipo | C8: Q 0 | D8: — | E8: 0
A9: Desarrollo de la plataforma GAMMA | B9: Proyecto de graduación MBIA · UVG | C9: Q 0 | D9: — | E9: 0
A10: COSTO TOTAL DEL PROYECTO | E10: =SUM(E5:E9) -> 1648.5552
A12: Notas de transparencia (no incluidas en el costo total)
A13: Costo de oportunidad del desarrollo | B13: GAMMA fue desarrollado como proyecto de graduación (MBIA-UVG) sin costo de desarrollo para CMI. Si se hubiera contratado con un proveedor externo, el desarrollo de una plataforma equivalente (backend, frontend, IA, arquitectura de datos) habría representado una inversión estimada en el rango de Q80,000–Q150,000 en el mercado guatemalteco, fuera del alcance de este ROI por tratarse de trabajo académico no facturado.
A14: Costos operativos futuros — fuera de alcance | B14: Este análisis refleja el costo de proyecto (construcción, pruebas y despliegue), no un modelo de costos operativos continuos. El hosting VPS más allá de la puesta en productivo (Q150/mes recurrente), así como las guías de actualización de índice y reentrenamiento del clasificador (ver Recomendaciones), son costos operativos futuros no incluidos en este ROI de proyecto.

Sheet ROI Consolidado
A1: RESUMEN FINANCIERO CONSOLIDADO — ROI
A2: Todos los beneficios se actualizan automáticamente al cambiar los supuestos
A4: Concepto | B4: Basado en Promedio | C4: Basado en Mediana | D4: Notas
A5: Costo hora-gestor CMI (Q/hora) | B5: ='B1 - Ahorro Tiempo'!B11 -> 87.672115 | C5: ='B1 - Ahorro Tiempo'!C11 -> 87.672115 | D5: Calculado en hoja Supuestos
A6: Tiempo PRE-GAMMA (hrs/solicitud) | B6: ='B1 - Ahorro Tiempo'!B5 -> 3.3437 | C6: ='B1 - Ahorro Tiempo'!C5 -> 2.8167 | D6: Promedio real 353 solicitudes (baseline 16 feb–16 jun)
A7: Tiempo POST-GAMMA (hrs/solicitud) | B7: ='B1 - Ahorro Tiempo'!B6 -> 1.4444 | C7: ='B1 - Ahorro Tiempo'!C6 -> 1.3083 | D7: Promedio real 84 solicitudes (post 18 jun–18 jul, sin outliers)
A8: Reducción porcentual de tiempo | B8: ='B1 - Ahorro Tiempo'!B8 -> 0.56802345 | C8: ='B1 - Ahorro Tiempo'!C8 -> 0.53552029 | D8: Mayor = mayor ahorro relativo
A9: AHORRO ANUAL B1 — Tiempo (Q) | B9: ='B1 - Ahorro Tiempo'!B12 -> 493385.87 | C9: ='B1 - Ahorro Tiempo'!C12 -> 391840.81 | D9: Anualizado sobre 2,963 sol./año
A10: AHORRO ANUAL B1 — Tiempo (USD) | B10: ='B1 - Ahorro Tiempo'!B13 -> 63662.693 | C10: ='B1 - Ahorro Tiempo'!C13 -> 50560.104 | D10: Tipo de cambio Q7.75
A11: Costo total del proyecto (Q) | B11: ='Costos del Proyecto'!E10 -> 1648.5552 | C11: ='Costos del Proyecto'!E10 -> 1648.5552 | D11: Vinculado a hoja Costos
A12: ROI Año 1 ((Beneficio−Costo)/Costo) | B12: =(B9-B11)/B11 -> 298.28381 | C12: =(C9-C11)/C11 -> 236.68741 | D12: Inversión se recupera casi inmediatamente
A13: Período de recuperación (días) | B13: =B11/(B9/12)*30 -> 1.2028716 | C13: =C11/(C9/12)*30 -> 1.5145943 | D13: Entre el primer y segundo día de uso
A15: Nota de validación
A16: Los datos post-GAMMA cubren el mes completo de prueba (18 jun–18 jul 2026, 84 solicitudes reales), excluyendo 34 solicitudes en cola durante el período de vacaciones (23 jun–1 jul) sin procesamiento activo con GAMMA. La diferencia frente al baseline es estadísticamente significativa (prueba U de Mann-Whitney, p < 0.0001; IC 95% no traslapados — ver hoja "Análisis Estadístico"). El volumen anual usa 2025 como referencia (2,963 solicitudes); actualizar con dato 2026 cuando esté disponible.

Sheet Análisis Estadístico
A1: ANÁLISIS ESTADÍSTICO — VALIDEZ DE LA COMPARACIÓN PRE/POST GAMMA
A2: Justificación estadística para la comparación de ventanas de observación desiguales
A4: 1. ESTADÍSTICA DESCRIPTIVA — TIEMPO EFECTIVO GESTOR (hrs/solicitud) | I4: Chart data — Tiempo Gestor
A5: Grupo | B5: n | C5: Media | D5: Mediana | E5: Desv. Estándar | F5: IC 95% inferior | G5: IC 95% superior | I5: Grupo | J5: Media (hrs)
A6: PRE-GAMMA (baseline) | B6: 353 | C6: 3.3437 | D6: 2.8167 | E6: 2.5713 | F6: 3.0754 | G6: 3.6119 | I6: PRE-GAMMA | J6: 3.3437
A7: POST-GAMMA | B7: 84 | C7: 1.4444 | D7: 1.3083 | E7: 1.0265 | F7: 1.2249 | G7: 1.664 | I7: POST-GAMMA | J7: 1.4444
F8: Fuente: Tiempos_post_GAMMA_DEN.xlsx (post) y ENERGIA_KPI_MATERIALES_BD.xlsx (pre) · Datos reales, no muestreados — censo completo del período
A10: 2. PRUEBAS DE SIGNIFICANCIA ESTADÍSTICA | I10: Chart data — Tasa diaria
A11: Prueba | B11: Estadístico | C11: Valor p | I11: Período | J11: Sol./día
A12: Prueba U de Mann-Whitney (no paramétrica — recomendada, datos sesgados: media > mediana) | B12: 21682 | C12: 2.196962e-11 | I12: PRE-GAMMA | J12: 2.92
A13: Prueba t de Welch (referencia, varianzas desiguales) | B13: 10.7395 | C13: 2.404514e-23 | I13: POST-GAMMA | J13: 4
A14: Interpretación
A15: p < 0.0001 en ambas pruebas: la probabilidad de que la reducción observada (3.34h → 1.44h) se deba al azar o al menor tamaño de la ventana post-GAMMA es prácticamente nula. Los IC 95% de ambos grupos no se traslapan (PRE: 3.08–3.61 · POST: 1.22–1.66), reforzando que la diferencia es robusta.
A18: 3. NORMALIZACIÓN POR TASA DIARIA (independiente de la duración de la ventana)
A19: Período | B19: Días calendario | C19: n solicitudes | D19: Solicitudes / día
A20: PRE-GAMMA (15 feb–17 jun) | B20: 121 | C20: 353 | D20: 2.92
A21: POST-GAMMA (18 jun–18 jul, sin outliers) | B21: 21 | C21: 84 | D21: 4
A22: La tasa diaria de atención fue mayor en el período post-GAMMA — el equipo sostuvo más volumen relativo con menos horas por solicitud.
A24: 4. NOTA METODOLÓGICA
A25: Ambos conjuntos corresponden al universo completo de solicitudes procesadas en su período — no son una muestra probabilística, por lo que no aplica error de muestreo. La ventana post-GAMMA es más corta por restricción de cronograma del proyecto de graduación; se recomienda extender el monitoreo como trabajo futuro.
