Workbook
Name MAT_TYPE: [1]DATA_CUSA!$C$3:$C$9
Name PAIS_IP: '[2]Plantilla IP'!#REF!
Name RAMO: [1]DATA_CUSA!$A$3
Name SOC_406: [1]CAMPOS406!$C$7:$C$11
Name UMB: [1]DATA_CUSA!$E$3:$E$547

Sheet Plantilla
A1: Vista_Datos 1 | B1: Vista_Datos 1 | C1: Vista_Datos 1 | D1: Vista_Datos 1 | E1: Vista_Datos 1 | F1: Vista_Datos 1 | G1: Vista_Datos 1 | H1: Vista_Datos 2 | I1: Vista_Datos 2 | J1: Vista_Datos 2 | L1: Vista_Compras | M1: Vista_Compras | N1: Vista_Compras | O1: Vista_Compras | P1: Vista_Dat.ce/Almacenam.1 | R1: Vista_planificación | S1: Vista_planificación | T1: Vista_planificación | U1: Vista_planificación | V1: Vista_planificación | W1: Vista_planificación | X1: Vista_planificación | Y1: Vista_planificación | Z1: Vista_Dat.ce/Almacenam.2 | AA1: Vista_Dat.ce/Almacenam.2 | AE1: Vista_Contabilidad 1 | AF1: Vista_Contabilidad 1 | AH1: Vista_Contabilidad 1 | AI1: Vista_Datos 1 | AJ1: Vista_Contabilidad 1
A2: Ramo | B2: Tipo de material | C2: Texto breve de material (máximo 40 caracteres) | D2: Unidad de medida base | E2: Grupo de artículos COMPLETA DATOS MAESTROS | F2: Número de material antiguo MARA-BISMT | G2: Sector COMPLETA DATOS MAESTROS | H2: Información de fabricación/inspección COMPLETA DATOS MAESTROS | I2: Denominación de estándar COMPLETA DATOS MAESTROS | J2: Materia COMPLETA DATOS MAESTROS | K2: Centro | L2: Grupo de compras COMPLETA DATOS MAESTROS | M2: ID de impuestos material | N2: Ind. Ped.autom. COMPLETA DATOS MAESTROS | O2: Tmpo. Tratamiento EM COMPLETA DATOS MAESTROS | P2: Almacén | Q2: Característica de planificación de necesidades MARC-DISMM | R2: Punto de pedido MARC-MINBE | S2: Planificador de necesidades MARC-DISPO | T2: Tamaño de lote de planificación de necesidades MARC-DISLS | U2: Tamaño de lote mínimo MARC-BSTMI | V2: Tamaño de lote máximo MARC-BSTMA | W2: Stock máximo MARC-MABST | X2: Plazo de entrega previsto en días MARC-PLIFZ | Y2: Grupo de verificación p.verificación de disponibilidad MARC-MTVFP | Z2: Ubicación | AA2: Centro de beneficio COMPLETA DATOS MAESTROS | AB2: Numero Almacen | AC2: Tipo de Almacen | AD2: Ubicación | AE2: Tipo de valoración COMPLETA DATOS MAESTROS | AF2: Categoría de valoración COMPLETA DATOS MAESTROS | AG2: Precio variable | AH2: Indicador de control de precios COMPLETA DATOS MAESTROS | AI2: Texto largo de material | AJ2: Clase de valoración COMPLETA DATOS MAESTROS | AK2: Observaciones
A3: =+_xlfn.XLOOKUP(I3,Clases!A:A,Clases!O:O,0,0,1) -> E | B3: =+_xlfn.XLOOKUP(I3,Clases!A:A,Clases!Q:Q,0,0,1) -> ZSUM | C3: PAÑO:LIMPIA;PANTALLA;MICROFIBRA;XL | D3: UN | E3: =+_xlfn.XLOOKUP(I3,Clases!A:A,Clases!N:N,0,0,1) -> SUM231200 | G3: =+_xlfn.XLOOKUP(I3,Clases!A:A,Clases!P:P,0,0,1) -> 50 | H3: =+_xlfn.XLOOKUP(I3,Clases!A:A,Clases!R:R,0,0,1) -> 47131800 | I3: 038710 | J3: =+_xlfn.XLOOKUP(I3,Clases!A:A,Clases!M:M,0,0,1) -> CMI02130200 | K3: 6000 | L3: X20 | M3: 1 | N3: X | O3: 7 | P3: 1000 | Q3: ND | Y3: Y2 | AA3: =+_xlfn.CONCAT(K3,"01") -> 600001 | AB3: 601 | AC3: T01 | AE3: =+IF(B3="ZHER","M",IF(B3="ZRPI","C","")) | AF3: 3022 | AG3: 1 | AH3: V | AI3: PAÑO DE MICROFIBRA TAMAÑO XL PARA LIMPIEZA DE PANTALLAS; MARCA WHOOSH; PRESENTACIÓN EN PAQUETE | AJ3: =+IF(B3="ZHER","NUEVAHER",IF(B3="ZRPI","NUEVOREP",""))
A4: =+_xlfn.XLOOKUP(I4,Clases!A:A,Clases!O:O,0,0,1) -> E | B4: =+_xlfn.XLOOKUP(I4,Clases!A:A,Clases!Q:Q,0,0,1) -> ZSEG | C4: CAMISA:ALGODON;SOLDADOR;TALLA;M | D4: UN | E4: =+_xlfn.XLOOKUP(I4,Clases!A:A,Clases!N:N,0,0,1) -> SEG221100 | G4: =+_xlfn.XLOOKUP(I4,Clases!A:A,Clases!P:P,0,0,1) -> 50 | H4: =+_xlfn.XLOOKUP(I4,Clases!A:A,Clases!R:R,0,0,1) -> 53101602 | I4: 047577 | J4: =+_xlfn.XLOOKUP(I4,Clases!A:A,Clases!M:M,0,0,1) -> CMI02170400 | K4: 6E91 | L4: X19 | M4: 1 | N4: X | O4: 7 | P4: 1000 | Q4: ND | Y4: Y2 | AA4: =+_xlfn.CONCAT(K4,"01") -> 6E9101 | AB4: 6ET | AC4: T01 | AE4: =+IF(B4="ZHER","M",IF(B4="ZRPI","C","")) | AF4: 3141 | AG4: 1 | AH4: V | AI4: CAMISA DE SEGURIDAD PARA SOLDADOR; MARCA STANCO; MATERIAL 100% ALGODON; TALLA M | AJ4: =+IF(B4="ZHER","NUEVAHER",IF(B4="ZRPI","NUEVOREP",""))
A5: =+_xlfn.XLOOKUP(I5,Clases!A:A,Clases!O:O,0,0,1) -> E | B5: =+_xlfn.XLOOKUP(I5,Clases!A:A,Clases!Q:Q,0,0,1) -> ZSEG | C5: CAMISA:ALGODON;SOLDADOR;TALLA;L | D5: UN | E5: =+_xlfn.XLOOKUP(I5,Clases!A:A,Clases!N:N,0,0,1) -> SEG221100 | G5: =+_xlfn.XLOOKUP(I5,Clases!A:A,Clases!P:P,0,0,1) -> 50 | H5: =+_xlfn.XLOOKUP(I5,Clases!A:A,Clases!R:R,0,0,1) -> 53101602 | I5: 047577 | J5: =+_xlfn.XLOOKUP(I5,Clases!A:A,Clases!M:M,0,0,1) -> CMI02170400 | K5: 6E91 | L5: X19 | M5: 1 | N5: X | O5: 7 | P5: 1000 | Q5: ND | Y5: Y2 | AA5: =+_xlfn.CONCAT(K5,"01") -> 6E9101 | AB5: 6ET | AC5: T01 | AE5: =+IF(B5="ZHER","M",IF(B5="ZRPI","C","")) | AF5: 3141 | AG5: 1 | AH5: V | AI5: CAMISA DE SEGURIDAD PARA SOLDADOR; MARCA STANCO; MATERIAL 100% ALGODON; TALLA L | AJ5: =+IF(B5="ZHER","NUEVAHER",IF(B5="ZRPI","NUEVOREP",""))
A6: =+_xlfn.XLOOKUP(I6,Clases!A:A,Clases!O:O,0,0,1) -> E | B6: =+_xlfn.XLOOKUP(I6,Clases!A:A,Clases!Q:Q,0,0,1) -> ZSEG | C6: CAMISA:ALGODON;SOLDADOR;TALLA;XL | D6: UN | E6: =+_xlfn.XLOOKUP(I6,Clases!A:A,Clases!N:N,0,0,1) -> SEG221100 | G6: =+_xlfn.XLOOKUP(I6,Clases!A:A,Clases!P:P,0,0,1) -> 50 | H6: =+_xlfn.XLOOKUP(I6,Clases!A:A,Clases!R:R,0,0,1) -> 53101602 | I6: 047577 | J6: =+_xlfn.XLOOKUP(I6,Clases!A:A,Clases!M:M,0,0,1) -> CMI02170400 | K6: 6E91 | L6: X19 | M6: 1 | N6: X | O6: 7 | P6: 1000 | Q6: ND | Y6: Y2 | AA6: =+_xlfn.CONCAT(K6,"01") -> 6E9101 | AB6: 6ET | AC6: T01 | AE6: =+IF(B6="ZHER","M",IF(B6="ZRPI","C","")) | AF6: 3141 | AG6: 1 | AH6: V | AI6: CAMISA DE SEGURIDAD PARA SOLDADOR; MARCA STANCO; MATERIAL 100% ALGODON; TALLA XL | AJ6: =+IF(B6="ZHER","NUEVAHER",IF(B6="ZRPI","NUEVOREP",""))

Sheet Clases
A1: Código | B1: Denominación | C1: Código Completo | D1: Categoría CMI | E1: Clave de Valores de Compras | F1: Unidad de Negocio | G1: Grupo de Artículos | H1: Ramo | I1: Sector | J1: Tipo de Material | K1: UNSPSC | L1: ID | M1: Categoría CMI | N1: Grupo de Artículos | O1: Ramo | P1: Sector | Q1: Tipo de Material | R1: UNSPSC
A2: 053111 | B2: PINTURAS:DECORATIVAS | D2: CMI01030400 - Otro-Mobiliario | F2: DEN | G2: ART371000 - Obras de arte | H2: E - Energía | I2: 50 - Otros | J2: ZART - Obras de arte | K2: 60121001 - Pinturas | L2: 6740 | M2: =+LEFT(D2,11) -> CMI01030400 | N2: =+LEFT(G2,9) -> ART371000 | O2: =+LEFT(H2,1) -> E | P2: =+LEFT(I2,2) -> 50 | Q2: =+LEFT(J2,4) -> ZART | R2: =+LEFT(K2,8) -> 60121001
A3: 010535 | B3: GRIFO | D3: CMI02050200 - Artefactos Sanitarios | F3: DEN | G3: CON251100 - Artefactos Sanitario | H3: E - Energía | I3: 50 - Otros | J3: ZCON - Materiales d/Construcción | K3: 30181700 - Grifos. | L3: 6741 | M3: =+LEFT(D3,11) -> CMI02050200 | N3: =+LEFT(G3,9) -> CON251100 | O3: =+LEFT(H3,1) -> E | P3: =+LEFT(I3,2) -> 50 | Q3: =+LEFT(J3,4) -> ZCON | R3: =+LEFT(K3,8) -> 30181700
A4: 010648 | B4: DUCHA DE BAÑO | D4: CMI02050100 - Accesorios | F4: DEN | G4: CON251100 - Artefactos Sanitario | H4: E - Energía | I4: 50 - Otros | J4: ZCON - Materiales d/Construcción | K4: 30181801 - Pomo de ducha | L4: 6742 | M4: =+LEFT(D4,11) -> CMI02050100 | N4: =+LEFT(G4,9) -> CON251100 | O4: =+LEFT(H4,1) -> E | P4: =+LEFT(I4,2) -> 50 | Q4: =+LEFT(J4,4) -> ZCON | R4: =+LEFT(K4,8) -> 30181801
A5: 015238 | B5: DEPOSITO | D5: CMI02090600 - Hidraulicos_Neumaticos | F5: DEN | G5: CON251000 - Accesorios | H5: E - Energía | I5: 50 - Otros | J5: ZCON - Materiales d/Construcción | K5: 24111810 - Tanques de almacenamiento agua | L5: 6743 | M5: =+LEFT(D5,11) -> CMI02090600 | N5: =+LEFT(G5,9) -> CON251000 | O5: =+LEFT(H5,1) -> E | P5: =+LEFT(I5,2) -> 50 | Q5: =+LEFT(J5,4) -> ZCON | R5: =+LEFT(K5,8) -> 24111810
A6: 015567 | B6: ARENA:CONSTRUCCION | D6: CMI02051500 - Piedrín y Arena | F6: DEN | G6: SUM231200 - Consumibles | H6: E - Energía | I6: 50 - Otros | J6: ZCON - Materiales d/Construcción | K6: 11111701 - Arena de sílice | L6: 6744 | M6: =+LEFT(D6,11) -> CMI02051500 | N6: =+LEFT(G6,9) -> SUM231200 | O6: =+LEFT(H6,1) -> E | P6: =+LEFT(I6,2) -> 50 | Q6: =+LEFT(J6,4) -> ZCON | R6: =+LEFT(K6,8) -> 11111701
A7: 015612 | B7: AZULEJOS:SUELO;CERAMICA | D7: CMI02051700 - Pisos y Azulejos | E7: 6 | F7: DEN | G7: SUM231200 - Consumibles | H7: E - Energía | I7: 50 - Otros | J7: ZCON - Materiales d/Construcción | K7: 30131704 - Losas o baldosas de cerámica | L7: 6745 | M7: =+LEFT(D7,11) -> CMI02051700 | N7: =+LEFT(G7,9) -> SUM231200 | O7: =+LEFT(H7,1) -> E | P7: =+LEFT(I7,2) -> 50 | Q7: =+LEFT(J7,4) -> ZCON | R7: =+LEFT(K7,8) -> 30131704
A8: 045346 | B8: CURADOR:CONCRETO | D8: CMI02180300 - Otros químicos | F8: DEN | G8: CON251300 - Concret/cemento/Adit | H8: E - Energía | I8: 50 - Otros | J8: ZCON - Materiales d/Construcción | K8: 12162301 - Agentes curado trans. por agua | L8: 6746 | M8: =+LEFT(D8,11) -> CMI02180300 | N8: =+LEFT(G8,9) -> CON251300 | O8: =+LEFT(H8,1) -> E | P8: =+LEFT(I8,2) -> 50 | Q8: =+LEFT(J8,4) -> ZCON | R8: =+LEFT(K8,8) -> 12162301
A9: 045409 | B9: PINTURA:ACRILICA | D9: CMI02051600 - Pinturas y Solventes | F9: DEN | G9: SUM231200 - Consumibles | H9: E - Energía | I9: 50 - Otros | J9: ZCON - Materiales d/Construcción | K9: 31211508 - Pinturas acrílicas | L9: 6747 | M9: =+LEFT(D9,11) -> CMI02051600 | N9: =+LEFT(G9,9) -> SUM231200 | O9: =+LEFT(H9,1) -> E | P9: =+LEFT(I9,2) -> 50 | Q9: =+LEFT(J9,4) -> ZCON | R9: =+LEFT(K9,8) -> 31211508
A10: 045555 | B10: COMPUESTO:SELLANTE | D10: CMI02051600 - Pinturas y Solventes | F10: DEN | G10: SUM231200 - Consumibles | H10: E - Energía | I10: 50 - Otros | J10: ZCON - Materiales d/Construcción | K10: 31201600 - Otros adhesivos y selladores | L10: 6748 | M10: =+LEFT(D10,11) -> CMI02051600 | N10: =+LEFT(G10,9) -> SUM231200 | O10: =+LEFT(H10,1) -> E | P10: =+LEFT(I10,2) -> 50 | Q10: =+LEFT(J10,4) -> ZCON | R10: =+LEFT(K10,8) -> 31201600
A11: 050395 | B11: LAMINA DE PLASTICO | D11: CMI03080500 - Otros-Empaques Especializados | F11: DEN | G11: SUM231200 - Consumibles | H11: E - Energía | I11: 50 - Otros | J11: ZCON - Materiales d/Construcción | K11: 30102015 - Lámina de plástico | L11: 6749 | M11: =+LEFT(D11,11) -> CMI03080500 | N11: =+LEFT(G11,9) -> SUM231200 | O11: =+LEFT(H11,1) -> E | P11: =+LEFT(I11,2) -> 50 | Q11: =+LEFT(J11,4) -> ZCON | R11: =+LEFT(K11,8) -> 30102015
A12: 050631 | B12: ANGULO:ALUMINIO | D12: CMI02051400 - Perfiles | F12: DEN | G12: SUM231200 - Consumibles | H12: E - Energía | I12: 50 - Otros | J12: ZCON - Materiales d/Construcción | K12: 30101506 - Ángulos de aluminio | L12: 6750 | M12: =+LEFT(D12,11) -> CMI02051400 | N12: =+LEFT(G12,9) -> SUM231200 | O12: =+LEFT(H12,1) -> E | P12: =+LEFT(I12,2) -> 50 | Q12: =+LEFT(J12,4) -> ZCON | R12: =+LEFT(K12,8) -> 30101506
A13: 050751 | B13: VIGA | D13: CMI02051400 - Perfiles | F13: DEN | G13: SUM231200 - Consumibles | H13: E - Energía | I13: 50 - Otros | J13: ZCON - Materiales d/Construcción | K13: 30101700 - Vigas | L13: 6751 | M13: =+LEFT(D13,11) -> CMI02051400 | N13: =+LEFT(G13,9) -> SUM231200 | O13: =+LEFT(H13,1) -> E | P13: =+LEFT(I13,2) -> 50 | Q13: =+LEFT(J13,4) -> ZCON | R13: =+LEFT(K13,8) -> 30101700
A14: 081807 | B14: TABLON | D14: CMI02051100 - Madera y derivados | F14: DEN | G14: SUM231200 - Consumibles | H14: E - Energía | I14: 50 - Otros | J14: ZCON - Materiales d/Construcción | K14: 30103605 - Tablones de madera | L14: 6752 | M14: =+LEFT(D14,11) -> CMI02051100 | N14: =+LEFT(G14,9) -> SUM231200 | O14: =+LEFT(H14,1) -> E | P14: =+LEFT(I14,2) -> 50 | Q14: =+LEFT(J14,4) -> ZCON | R14: =+LEFT(K14,8) -> 30103605
A15: 083674 | B15: PINTURA:REVESTIMIENTO | D15: CMI02051600 - Pinturas y Solventes | F15: DEN | G15: REP211100 - Rpto. AutomMecanico | H15: E - Energía | I15: 50 - Otros | J15: ZCON - Materiales d/Construcción | K15: 31211504 - Pinturas de revestimiento | L15: 6753 | M15: =+LEFT(D15,11) -> CMI02051600 | N15: =+LEFT(G15,9) -> REP211100 | O15: =+LEFT(H15,1) -> E | P15: =+LEFT(I15,2) -> 50 | Q15: =+LEFT(J15,4) -> ZCON | R15: =+LEFT(K15,8) -> 31211504
A16: 085771 | B16: ADITIVO | D16: CMI02050400 - Concreto, Cemento y Aditivos | F16: DEN | G16: SUM231200 - Consumibles | H16: E - Energía | I16: 50 - Otros | J16: ZCON - Materiales d/Construcción | K16: 12162305 - Aditivo de concreto | L16: 6754 | M16: =+LEFT(D16,11) -> CMI02050400 | N16: =+LEFT(G16,9) -> SUM231200 | O16: =+LEFT(H16,1) -> E | P16: =+LEFT(I16,2) -> 50 | Q16: =+LEFT(J16,4) -> ZCON | R16: =+LEFT(K16,8) -> 12162305
A17: 086456 | B17: CANAL | D17: CMI02051400 - Perfiles | F17: DEN | G17: SUM231200 - Consumibles | H17: E - Energía | I17: 50 - Otros | J17: ZCON - Materiales d/Construcción | K17: 30101800 - Conductos | L17: 6755 | M17: =+LEFT(D17,11) -> CMI02051400 | N17: =+LEFT(G17,9) -> SUM231200 | O17: =+LEFT(H17,1) -> E | P17: =+LEFT(I17,2) -> 50 | Q17: =+LEFT(J17,4) -> ZCON | R17: =+LEFT(K17,8) -> 30101800
A18: 088536 | B18: POSTE | D18: CMI02051300 - Otros-Mat de Construcción | F18: DEN | G18: SEG221000 - EquipSeguridad Indus | H18: E - Energía | I18: 50 - Otros | J18: ZCON - Materiales d/Construcción | K18: 30102900 - Pilares | L18: 6756 | M18: =+LEFT(D18,11) -> CMI02051300 | N18: =+LEFT(G18,9) -> SEG221000 | O18: =+LEFT(H18,1) -> E | P18: =+LEFT(I18,2) -> 50 | Q18: =+LEFT(J18,4) -> ZCON | R18: =+LEFT(K18,8) -> 30102900
A19: 088802 | B19: VARILLA | D19: CMI02050700 - Hierro | F19: DEN | G19: SUM231100 - Accesorios Mecánicos | H19: E - Energía | I19: 50 - Otros | J19: ZCON - Materiales d/Construcción | K19: 30102400 - Varillas | L19: 6757 | M19: =+LEFT(D19,11) -> CMI02050700 | N19: =+LEFT(G19,9) -> SUM231100 | O19: =+LEFT(H19,1) -> E | P19: =+LEFT(I19,2) -> 50 | Q19: =+LEFT(J19,4) -> ZCON | R19: =+LEFT(K19,8) -> 30102400
... A67: 050809 | B67: LAMINA:HIERRO | D67: CMI02051000 - Laminas | F67: DEN | G67: CON251800 - Laminas | H67: E - Energía | I67: 50 - Otros | J67: ZCON - Materiales d/Construcción | K67: 30102203 - Placa de hierro | L67: 6805 | M67: =+LEFT(D67,11) -> CMI02051000 | N67: =+LEFT(G67,9) -> CON251800 | O67: =+LEFT(H67,1) -> E | P67: =+LEFT(I67,2) -> 50 | Q67: =+LEFT(J67,4) -> ZCON | R67: =+LEFT(K67,8) -> 30102203
A68: 050814 | B68: LAMINA:ACERO | D68: CMI02051000 - Laminas | E68: 6 | F68: DEN | G68: CON251800 - Laminas | H68: E - Energía | I68: 50 - Otros | J68: ZCON - Materiales d/Construcción | K68: 30102004 - Lámina de acero | L68: 6806 | M68: =+LEFT(D68,11) -> CMI02051000 | N68: =+LEFT(G68,9) -> CON251800 | O68: =+LEFT(H68,1) -> E | P68: =+LEFT(I68,2) -> 50 | Q68: =+LEFT(J68,4) -> ZCON | R68: =+LEFT(K68,8) -> 30102004
A69: 050857 | B69: PERFIL:HIERRO | D69: CMI02051400 - Perfiles | F69: DEN | G69: CON252000 - Perfiles | H69: E - Energía | I69: 50 - Otros | J69: ZCON - Materiales d/Construcción | K69: 30102303 - Perfiles de hierro | L69: 6807 | M69: =+LEFT(D69,11) -> CMI02051400 | N69: =+LEFT(G69,9) -> CON252000 | O69: =+LEFT(H69,1) -> E | P69: =+LEFT(I69,2) -> 50 | Q69: =+LEFT(J69,4) -> ZCON | R69: =+LEFT(K69,8) -> 30102303
A70: 050886 | B70: LAMINA:METAL | D70: CMI02051000 - Laminas | F70: DEN | G70: CON251800 - Laminas | H70: E - Energía | I70: 50 - Otros | J70: ZCON - Materiales d/Construcción | K70: 30102000 - Hoja | L70: 6808 | M70: =+LEFT(D70,11) -> CMI02051000 | N70: =+LEFT(G70,9) -> CON251800 | O70: =+LEFT(H70,1) -> E | P70: =+LEFT(I70,2) -> 50 | Q70: =+LEFT(J70,4) -> ZCON | R70: =+LEFT(K70,8) -> 30102000
A71: 050902 | B71: LAMINA:ACERO INOX | D71: CMI02051000 - Laminas | F71: DEN | G71: CON251800 - Laminas | H71: E - Energía | I71: 50 - Otros | J71: ZCON - Materiales d/Construcción | K71: 30102005 - Lámina de acero inoxidable | L71: 6809 | M71: =+LEFT(D71,11) -> CMI02051000 | N71: =+LEFT(G71,9) -> CON251800 | O71: =+LEFT(H71,1) -> E | P71: =+LEFT(I71,2) -> 50 | Q71: =+LEFT(J71,4) -> ZCON | R71: =+LEFT(K71,8) -> 30102005
A72: 050906 | B72: LAMINA:MADERA | D72: CMI02051000 - Laminas | F72: DEN | G72: CON251900 - Madera y derivados | H72: E - Energía | I72: 50 - Otros | J72: ZCON - Materiales d/Construcción | K72: 30103604 - Revestimiento o láminas madera | L72: 6810 | M72: =+LEFT(D72,11) -> CMI02051000 | N72: =+LEFT(G72,9) -> CON251900 | O72: =+LEFT(H72,1) -> E | P72: =+LEFT(I72,2) -> 50 | Q72: =+LEFT(J72,4) -> ZCON | R72: =+LEFT(K72,8) -> 30103604
A73: 051265 | B73: VIGA:CEMENTO | D73: CMI02050400 - Concreto, Cemento y Aditivos | F73: DEN | G73: CON251300 - Concret/cemento/Adit | H73: E - Energía | I73: 50 - Otros | J73: ZCON - Materiales d/Construcción | K73: 30101717 - Vigas de concreto | L73: 6811 | M73: =+LEFT(D73,11) -> CMI02050400 | N73: =+LEFT(G73,9) -> CON251300 | O73: =+LEFT(H73,1) -> E | P73: =+LEFT(I73,2) -> 50 | Q73: =+LEFT(J73,4) -> ZCON | R73: =+LEFT(K73,8) -> 30101717
A74: 067504 | B74: CAL HIDRATADA | D74: CMI02050400 - Concreto, Cemento y Aditivos | F74: DEN | G74: CON251300 - Concret/cemento/Adit | H74: E - Energía | I74: 50 - Otros | J74: ZCON - Materiales d/Construcción | K74: 30111607 - Cal viva | L74: 6812 | M74: =+LEFT(D74,11) -> CMI02050400 | N74: =+LEFT(G74,9) -> CON251300 | O74: =+LEFT(H74,1) -> E | P74: =+LEFT(I74,2) -> 50 | Q74: =+LEFT(J74,4) -> ZCON | R74: =+LEFT(K74,8) -> 30111607
A75: 067736 | B75: TIERRA | D75: CMI02051500 - Piedrín y Arena | F75: DEN | G75: CON252100 - Piedrín y Arena | H75: E - Energía | I75: 50 - Otros | J75: ZCON - Materiales d/Construcción | K75: 11111501 - Tierra | L75: 6813 | M75: =+LEFT(D75,11) -> CMI02051500 | N75: =+LEFT(G75,9) -> CON252100 | O75: =+LEFT(H75,1) -> E | P75: =+LEFT(I75,2) -> 50 | Q75: =+LEFT(J75,4) -> ZCON | R75: =+LEFT(K75,8) -> 11111501
A76: 070495 | B76: DIGESTOR | D76: CMI02051300 - Otros-Mat de Construcción | F76: DEN | G76: CON251000 - Accesorios | H76: E - Energía | I76: 50 - Otros | J76: ZCON - Materiales d/Construcción | K76: 23151804 - React/fermentadores digestores | L76: 6814 | M76: =+LEFT(D76,11) -> CMI02051300 | N76: =+LEFT(G76,9) -> CON251000 | O76: =+LEFT(H76,1) -> E | P76: =+LEFT(I76,2) -> 50 | Q76: =+LEFT(J76,4) -> ZCON | R76: =+LEFT(K76,8) -> 23151804
A77: 071419 | B77: RETARDANTE AL FUEGO | D77: CMI02051300 - Otros-Mat de Construcción | F77: DEN | G77: CON252200 - Pinturas y solventes | H77: E - Energía | I77: 50 - Otros | J77: ZCON - Materiales d/Construcción | K77: 12162100 - Retardadores de llama | L77: 6815 | M77: =+LEFT(D77,11) -> CMI02051300 | N77: =+LEFT(G77,9) -> CON252200 | O77: =+LEFT(H77,1) -> E | P77: =+LEFT(I77,2) -> 50 | Q77: =+LEFT(J77,4) -> ZCON | R77: =+LEFT(K77,8) -> 12162100
A78: 071806 | B78: GEOMEMBRANA | D78: CMI02051300 - Otros-Mat de Construcción | F78: DEN | G78: CON251400 - Fijación y Anclajes | H78: E - Energía | I78: 50 - Otros | J78: ZCON - Materiales d/Construcción | K78: 30121701 - Geomalla | L78: 6816 | M78: =+LEFT(D78,11) -> CMI02051300 | N78: =+LEFT(G78,9) -> CON251400 | O78: =+LEFT(H78,1) -> E | P78: =+LEFT(I78,2) -> 50 | Q78: =+LEFT(J78,4) -> ZCON | R78: =+LEFT(K78,8) -> 30121701
A79: 071810 | B79: GEOTEXTIL | D79: CMI02051300 - Otros-Mat de Construcción | F79: DEN | G79: CON251400 - Fijación y Anclajes | H79: E - Energía | I79: 50 - Otros | J79: ZCON - Materiales d/Construcción | K79: 30121702 - Geotextil | L79: 6817 | M79: =+LEFT(D79,11) -> CMI02051300 | N79: =+LEFT(G79,9) -> CON251400 | O79: =+LEFT(H79,1) -> E | P79: =+LEFT(I79,2) -> 50 | Q79: =+LEFT(J79,4) -> ZCON | R79: =+LEFT(K79,8) -> 30121702
A80: 078852 | B80: GAVION COLCHON | D80: CMI02051300 - Otros-Mat de Construcción | F80: DEN | G80: CON252100 - Piedrín y Arena | H80: E - Energía | I80: 50 - Otros | J80: ZCON - Materiales d/Construcción | K80: 31163401 - Gavión | L80: 6818 | M80: =+LEFT(D80,11) -> CMI02051300 | N80: =+LEFT(G80,9) -> CON252100 | O80: =+LEFT(H80,1) -> E | P80: =+LEFT(I80,2) -> 50 | Q80: =+LEFT(J80,4) -> ZCON | R80: =+LEFT(K80,8) -> 31163401
... A135: 070102 | B135: INHIBIDOR CORROSION | D135: CMI02030100 - Grasas Industriales | F135: DEN | G135: LUB261000 - Grasas Industriales | H135: E - Energía | I135: 50 - Otros | J135: ZLUB - Combustibles y Lubricante | K135: 15121802 - Lubricante anti – corrosión | L135: 6873 | M135: =+LEFT(D135,11) -> CMI02030100 | N135: =+LEFT(G135,9) -> LUB261000 | O135: =+LEFT(H135,1) -> E | P135: =+LEFT(I135,2) -> 50 | Q135: =+LEFT(J135,4) -> ZLUB | R135: =+LEFT(K135,8) -> 15121802
A136: 073066 | B136: GRASA LUBRICANTE | D136: CMI02030300 - Lubricantes Industriales | E136: 6 | F136: DEN | G136: LUB261000 - Grasas Industriales | H136: E - Energía | I136: 10 - Energía | J136: ZLUB - Combustibles y Lubricante | K136: 27112914 - Lubricador de grasa | L136: 6874 | M136: =+LEFT(D136,11) -> CMI02030300 | N136: =+LEFT(G136,9) -> LUB261000 | O136: =+LEFT(H136,1) -> E | P136: =+LEFT(I136,2) -> 10 | Q136: =+LEFT(J136,4) -> ZLUB | R136: =+LEFT(K136,8) -> 27112914
A137: 087912 | B137: LUBRICANTE | D137: CMI02030300 - Lubricantes Industriales | F137: DEN | G137: LUB261200 - LubricanIndustriales | H137: E - Energía | I137: 50 - Otros | J137: ZLUB - Combustibles y Lubricante | K137: 15121501 - Aceite motor | L137: 6875 | M137: =+LEFT(D137,11) -> CMI02030300 | N137: =+LEFT(G137,9) -> LUB261200 | O137: =+LEFT(H137,1) -> E | P137: =+LEFT(I137,2) -> 50 | Q137: =+LEFT(J137,4) -> ZLUB | R137: =+LEFT(K137,8) -> 15121501
A138: 007055 | B138: ROSCADORA:ELECTRICA | D138: CMI01020300 - Equipo Industrial | F138: DEN | G138: SUM231400 - Herram d/Eléctricas | H138: E - Energía | I138: 50 - Otros | J138: ZMAQ - Maquinaria | K138: 23241642 - Roscadora de velocidad | L138: 6876 | M138: =+LEFT(D138,11) -> CMI01020300 | N138: =+LEFT(G138,9) -> SUM231400 | O138: =+LEFT(H138,1) -> E | P138: =+LEFT(I138,2) -> 50 | Q138: =+LEFT(J138,4) -> ZMAQ | R138: =+LEFT(K138,8) -> 23241642
A139: 086626 | B139: COMPRESOR | D139: CMI01020300 - Equipo Industrial | F139: DEN | G139: REP201100 - Rpto.Ind/Mecánicos | H139: E - Energía | I139: 50 - Otros | J139: ZMAQ - Maquinaria | K139: 40151600 - Compresores | L139: 6877 | M139: =+LEFT(D139,11) -> CMI01020300 | N139: =+LEFT(G139,9) -> REP201100 | O139: =+LEFT(H139,1) -> E | P139: =+LEFT(I139,2) -> 50 | Q139: =+LEFT(J139,4) -> ZMAQ | R139: =+LEFT(K139,8) -> 40151600
A140: 011646 | B140: EQUIPO;LIMPIEZA;ELEC | D140: CMI01020300 - Equipo Industrial | F140: DEN | G140: SUM231600 - Herramienta Mecánica | H140: E - Energía | I140: 50 - Otros | J140: ZMAQ - Maquinaria | K140: 72153504 - Limpieza chorro agua alta pres | L140: 6878 | M140: =+LEFT(D140,11) -> CMI01020300 | N140: =+LEFT(G140,9) -> SUM231600 | O140: =+LEFT(H140,1) -> E | P140: =+LEFT(I140,2) -> 50 | Q140: =+LEFT(J140,4) -> ZMAQ | R140: =+LEFT(K140,8) -> 72153504
A141: 003881 | B141: BOTE:INFLABLE | D141: CMI01060800 - Otros-Vehículos | F141: DEN | G141: MAQ351000 - Maquinaria | H141: E - Energía | I141: 50 - Otros | J141: ZMAQ - Maquinaria | K141: 25111516 - Bote de caucho inflable | L141: 6879 | M141: =+LEFT(D141,11) -> CMI01060800 | N141: =+LEFT(G141,9) -> MAQ351000 | O141: =+LEFT(H141,1) -> E | P141: =+LEFT(I141,2) -> 50 | Q141: =+LEFT(J141,4) -> ZMAQ | R141: =+LEFT(K141,8) -> 25111516
A142: 004593 | B142: CAMION:TOLVA | D142: CMI01060200 - Camiones | F142: DEN | G142: MAQ351000 - Maquinaria | H142: E - Energía | I142: 50 - Otros | J142: ZMAQ - Maquinaria | K142: 25101916 - Camión tolva | L142: 6880 | M142: =+LEFT(D142,11) -> CMI01060200 | N142: =+LEFT(G142,9) -> MAQ351000 | O142: =+LEFT(H142,1) -> E | P142: =+LEFT(I142,2) -> 50 | Q142: =+LEFT(J142,4) -> ZMAQ | R142: =+LEFT(K142,8) -> 25101916
A143: 005718 | B143: MOTOR FUERABORDA:GASOLINA | D143: CMI01060800 - Otros-Vehículos | F143: DEN | G143: MAQ351000 - Maquinaria | H143: E - Energía | I143: 50 - Otros | J143: ZMAQ - Maquinaria | K143: 26101515 - Motor fuera de borda gasolina | L143: 6881 | M143: =+LEFT(D143,11) -> CMI01060800 | N143: =+LEFT(G143,9) -> MAQ351000 | O143: =+LEFT(H143,1) -> E | P143: =+LEFT(I143,2) -> 50 | Q143: =+LEFT(J143,4) -> ZMAQ | R143: =+LEFT(K143,8) -> 26101515
A144: 006051 | B144: GENERADOR | D144: CMI01020300 - Equipo Industrial | F144: DEN | G144: MAQ351000 - Maquinaria | H144: E - Energía | I144: 50 - Otros | J144: ZMAQ - Maquinaria | K144: 26111600 - Generadores de potencia | L144: 6882 | M144: =+LEFT(D144,11) -> CMI01020300 | N144: =+LEFT(G144,9) -> MAQ351000 | O144: =+LEFT(H144,1) -> E | P144: =+LEFT(I144,2) -> 50 | Q144: =+LEFT(J144,4) -> ZMAQ | R144: =+LEFT(K144,8) -> 26111600
A145: 008727 | B145: MEZCLADOR:CONCRETO | D145: CMI01020300 - Equipo Industrial | F145: DEN | G145: MAQ351000 - Maquinaria | H145: E - Energía | I145: 50 - Otros | J145: ZMAQ - Maquinaria | K145: 22101901 - Mezcladoras o plantas concreto | L145: 6883 | M145: =+LEFT(D145,11) -> CMI01020300 | N145: =+LEFT(G145,9) -> MAQ351000 | O145: =+LEFT(H145,1) -> E | P145: =+LEFT(I145,2) -> 50 | Q145: =+LEFT(J145,4) -> ZMAQ | R145: =+LEFT(K145,8) -> 22101901
A146: 008353 | B146: QUEMADOR:HIERBA | D146: CMI01020300 - Equipo Industrial | F146: DEN | G146: MAQ351000 - Maquinaria | H146: E - Energía | I146: 50 - Otros | J146: ZMAQ - Maquinaria | K146: 21101504 - Desmalezadoras | L146: 6884 | M146: =+LEFT(D146,11) -> CMI01020300 | N146: =+LEFT(G146,9) -> MAQ351000 | O146: =+LEFT(H146,1) -> E | P146: =+LEFT(I146,2) -> 50 | Q146: =+LEFT(J146,4) -> ZMAQ | R146: =+LEFT(K146,8) -> 21101504
A147: 013584 | B147: ESTAMPADORA:CONTERA | D147: CMI02090500 - Herramientas Industriales | F147: DEN | G147: SUM231500 - Herramienta Manual | H147: E - Energía | I147: 50 - Otros | J147: ZMAQ - Maquinaria | K147: 27111607 - Herramientas de recalcar | L147: 6885 | M147: =+LEFT(D147,11) -> CMI02090500 | N147: =+LEFT(G147,9) -> SUM231500 | O147: =+LEFT(H147,1) -> E | P147: =+LEFT(I147,2) -> 50 | Q147: =+LEFT(J147,4) -> ZMAQ | R147: =+LEFT(K147,8) -> 27111607
A148: 008408 | B148: EQUIPO:APISONADORA | D148: CMI01020300 - Equipo Industrial | F148: DEN | G148: MAQ351000 - Maquinaria | H148: E - Energía | I148: 50 - Otros | J148: ZMAQ - Maquinaria | K148: 22101511 - Compactadores | L148: 6886 | M148: =+LEFT(D148,11) -> CMI01020300 | N148: =+LEFT(G148,9) -> MAQ351000 | O148: =+LEFT(H148,1) -> E | P148: =+LEFT(I148,2) -> 50 | Q148: =+LEFT(J148,4) -> ZMAQ | R148: =+LEFT(K148,8) -> 22101511
... A165: 060272 | B165: AL MAYOR:JUGUETE | D165: CMI02170300 - Otros-Suministros Personal | F165: DEN | G165: MER391100 - Art/evento especial | H165: E - Energía | I165: 50 - Otros | J165: ZMER - Mercadeo | K165: 60141000 - Juguetes | L165: 6903 | M165: =+LEFT(D165,11) -> CMI02170300 | N165: =+LEFT(G165,9) -> MER391100 | O165: =+LEFT(H165,1) -> E | P165: =+LEFT(I165,2) -> 50 | Q165: =+LEFT(J165,4) -> ZMER | R165: =+LEFT(K165,8) -> 60141000
A166: 1070051 | B166: REGALO CORPORATIVO | D166: CMI02040300 - Otros-Material POP | E166: 6 | F166: DEN | G166: MER391100 - Art/evento especial | H166: E - Energía | I166: 10 - Energía | J166: ZMER - Mercadeo | K166: 49101700 - Premios | L166: 6904 | M166: =+LEFT(D166,11) -> CMI02040300 | N166: =+LEFT(G166,9) -> MER391100 | O166: =+LEFT(H166,1) -> E | P166: =+LEFT(I166,2) -> 10 | Q166: =+LEFT(J166,4) -> ZMER | R166: =+LEFT(K166,8) -> 49101700
A167: 1144556 | B167: UTILES ESCOLARES | D167: CMI02160100 - Papelería y Útiles | F167: DEN | G167: MER391200 - Promocionales | H167: E - Energía | I167: 50 - Otros | J167: ZMER - Mercadeo | K167: 60100000 - Materia didácticos profes desa | L167: 6905 | M167: =+LEFT(D167,11) -> CMI02160100 | N167: =+LEFT(G167,9) -> MER391200 | O167: =+LEFT(H167,1) -> E | P167: =+LEFT(I167,2) -> 50 | Q167: =+LEFT(J167,4) -> ZMER | R167: =+LEFT(K167,8) -> 60100000
A168: 045637 | B168: BOTELLA:CON TAPA;SEGURIDAD | D168: CMI02170200 - Insumos Cafetería Oficinas | F168: DEN | G168: MER391200 - Promocionales | H168: E - Energía | I168: 50 - Otros | J168: ZMER - Mercadeo | K168: 24122002 - Botellas de plástico | L168: 6906 | M168: =+LEFT(D168,11) -> CMI02170200 | N168: =+LEFT(G168,9) -> MER391200 | O168: =+LEFT(H168,1) -> E | P168: =+LEFT(I168,2) -> 50 | Q168: =+LEFT(J168,4) -> ZMER | R168: =+LEFT(K168,8) -> 24122002
A169: 014472 | B169: LLAVERO | D169: CMI02170300 - Otros-Suministros Personal | F169: DEN | G169: MER391200 - Promocionales | H169: E - Energía | I169: 50 - Otros | J169: ZMER - Mercadeo | K169: 46171515 - Cadenas o estuches de llaves | L169: 6907 | M169: =+LEFT(D169,11) -> CMI02170300 | N169: =+LEFT(G169,9) -> MER391200 | O169: =+LEFT(H169,1) -> E | P169: =+LEFT(I169,2) -> 50 | Q169: =+LEFT(J169,4) -> ZMER | R169: =+LEFT(K169,8) -> 46171515
A170: 044921 | B170: JUGUETE:PIÑATA | D170: CMI02040400 - Promocionales | F170: DEN | G170: MER391200 - Promocionales | H170: E - Energía | I170: 50 - Otros | J170: ZMER - Mercadeo | K170: 60141019 - PIÑATA | L170: 6908 | M170: =+LEFT(D170,11) -> CMI02040400 | N170: =+LEFT(G170,9) -> MER391200 | O170: =+LEFT(H170,1) -> E | P170: =+LEFT(I170,2) -> 50 | Q170: =+LEFT(J170,4) -> ZMER | R170: =+LEFT(K170,8) -> 60141019
A171: 055266 | B171: IMPRESIÓN:PUBLICIDAD | D171: CMI02040400 - Promocionales | F171: DEN | G171: MER391100 - Art/evento especial | H171: E - Energía | I171: 50 - Otros | J171: ZMER - Mercadeo | K171: 82121512 - Impresión en relieve | L171: 6909 | M171: =+LEFT(D171,11) -> CMI02040400 | N171: =+LEFT(G171,9) -> MER391100 | O171: =+LEFT(H171,1) -> E | P171: =+LEFT(I171,2) -> 50 | Q171: =+LEFT(J171,4) -> ZMER | R171: =+LEFT(K171,8) -> 82121512
A172: 049249 | B172: MERMELADA | D172: CMI02060600 - Jaleas | F172: DEN | G172: MER391100 - Art/evento especial | H172: E - Energía | I172: 50 - Otros | J172: ZMER - Mercadeo | K172: 50192401 - Mermeladas preserv para fruta | L172: 6910 | M172: =+LEFT(D172,11) -> CMI02060600 | N172: =+LEFT(G172,9) -> MER391100 | O172: =+LEFT(H172,1) -> E | P172: =+LEFT(I172,2) -> 50 | Q172: =+LEFT(J172,4) -> ZMER | R172: =+LEFT(K172,8) -> 50192401
A173: 048750 | B173: CONSERVA | D173: CMI02060600 - Jaleas | F173: DEN | G173: MER391100 - Art/evento especial | H173: E - Energía | I173: 50 - Otros | J173: ZMER - Mercadeo | K173: 50171904 - Conserva | L173: 6911 | M173: =+LEFT(D173,11) -> CMI02060600 | N173: =+LEFT(G173,9) -> MER391100 | O173: =+LEFT(H173,1) -> E | P173: =+LEFT(I173,2) -> 50 | Q173: =+LEFT(J173,4) -> ZMER | R173: =+LEFT(K173,8) -> 50171904
A174: 048791 | B174: GALLETA:CAFÉ | D174: CMI02170300 - Otros-Suministros Personal | F174: DEN | G174: MER391100 - Art/evento especial | H174: E - Energía | I174: 50 - Otros | J174: ZMER - Mercadeo | K174: 50181900 - Pan galletas pastelitos dulces | L174: 6912 | M174: =+LEFT(D174,11) -> CMI02170300 | N174: =+LEFT(G174,9) -> MER391100 | O174: =+LEFT(H174,1) -> E | P174: =+LEFT(I174,2) -> 50 | Q174: =+LEFT(J174,4) -> ZMER | R174: =+LEFT(K174,8) -> 50181900
A175: 048557 | B175: CARDAMOMO | D175: CMI02170300 - Otros-Suministros Personal | F175: DEN | G175: MER391100 - Art/evento especial | H175: E - Energía | I175: 50 - Otros | J175: ZMER - Mercadeo | K175: 50171550 - Especies o extractos | L175: 6913 | M175: =+LEFT(D175,11) -> CMI02170300 | N175: =+LEFT(G175,9) -> MER391100 | O175: =+LEFT(H175,1) -> E | P175: =+LEFT(I175,2) -> 50 | Q175: =+LEFT(J175,4) -> ZMER | R175: =+LEFT(K175,8) -> 50171550
A176: 042498 | B176: ESTANTE;ALMACENAMIENTO | D176: CMI01030300 - Mobiliario y Equipo de oficina | F176: DEN | G176: MOB361000 - Mobiliario/Oficina | H176: E - Energía | I176: 10 - Energía | J176: ZMOB - Mobiliario | K176: 24112406 - Compartimentos caja/estantería | L176: 6914 | M176: =+LEFT(D176,11) -> CMI01030300 | N176: =+LEFT(G176,9) -> MOB361000 | O176: =+LEFT(H176,1) -> E | P176: =+LEFT(I176,2) -> 10 | Q176: =+LEFT(J176,4) -> ZMOB | R176: =+LEFT(K176,8) -> 24112406
A177: 016520 | B177: PANEL:INDICATOR | D177: CMI02090400 - Electrónicos | F177: DEN | G177: MOB361000 - Mobiliario/Oficina | H177: E - Energía | I177: 50 - Otros | J177: ZMOB - Mobiliario | K177: 39121103 - Paneles | L177: 6915 | M177: =+LEFT(D177,11) -> CMI02090400 | N177: =+LEFT(G177,9) -> MOB361000 | O177: =+LEFT(H177,1) -> E | P177: =+LEFT(I177,2) -> 50 | Q177: =+LEFT(J177,4) -> ZMOB | R177: =+LEFT(K177,8) -> 39121103
A178: 042310 | B178: ARMARIO | D178: CMI01030300 - Mobiliario y Equipo de oficina | E178: 6 | F178: DEN | G178: MOB361000 - Mobiliario/Oficina | H178: E - Energía | I178: 10 - Energía | J178: ZMOB - Mobiliario | K178: 56101530 - Gabinetes de almacenamiento | L178: 6916 | M178: =+LEFT(D178,11) -> CMI01030300 | N178: =+LEFT(G178,9) -> MOB361000 | O178: =+LEFT(H178,1) -> E | P178: =+LEFT(I178,2) -> 10 | Q178: =+LEFT(J178,4) -> ZMOB | R178: =+LEFT(K178,8) -> 56101530
A179: 042546 | B179: MESA:DE COMEDOR | D179: CMI02170200 - Insumos Cafetería Oficinas | F179: DEN | G179: MOB361000 - Mobiliario/Oficina | H179: E - Energía | I179: 50 - Otros | J179: ZMOB - Mobiliario | K179: 56101519 - Mesas | L179: 6917 | M179: =+LEFT(D179,11) -> CMI02170200 | N179: =+LEFT(G179,9) -> MOB361000 | O179: =+LEFT(H179,1) -> E | P179: =+LEFT(I179,2) -> 50 | Q179: =+LEFT(J179,4) -> ZMOB | R179: =+LEFT(K179,8) -> 56101519
A180: 088475 | B180: TARIMA | D180: CMI02051300 - Otros-Mat de Construcción | F180: DEN | G180: MOB361000 - Mobiliario/Oficina | H180: E - Energía | I180: 50 - Otros | J180: ZMOB - Mobiliario | K180: 30241601 - Tarima y acce de la tribuna | L180: 6918 | M180: =+LEFT(D180,11) -> CMI02051300 | N180: =+LEFT(G180,9) -> MOB361000 | O180: =+LEFT(H180,1) -> E | P180: =+LEFT(I180,2) -> 50 | Q180: =+LEFT(J180,4) -> ZMOB | R180: =+LEFT(K180,8) -> 30241601
A181: 042490 | B181: ESCRITORIO | D181: CMI01030300 - Mobiliario y Equipo de oficina | F181: DEN | G181: MOB361000 - Mobiliario/Oficina | H181: E - Energía | I181: 50 - Otros | J181: ZMOB - Mobiliario | K181: 56101703 - Escritorios | L181: 6919 | M181: =+LEFT(D181,11) -> CMI01030300 | N181: =+LEFT(G181,9) -> MOB361000 | O181: =+LEFT(H181,1) -> E | P181: =+LEFT(I181,2) -> 50 | Q181: =+LEFT(J181,4) -> ZMOB | R181: =+LEFT(K181,8) -> 56101703
A182: 065999 | B182: ESTRUCTURADO | D182: CMI01030300 - Mobiliario y Equipo de oficina | F182: DEN | G182: MOB361000 - Mobiliario/Oficina | H182: E - Energía | I182: 50 - Otros | J182: ZMOB - Mobiliario | K182: 31331100 - Cjtos estrs c/acabado ligado | L182: 6920 | M182: =+LEFT(D182,11) -> CMI01030300 | N182: =+LEFT(G182,9) -> MOB361000 | O182: =+LEFT(H182,1) -> E | P182: =+LEFT(I182,2) -> 50 | Q182: =+LEFT(J182,4) -> ZMOB | R182: =+LEFT(K182,8) -> 31331100
A183: 053542 | B183: REFRIGERADOR | D183: CMI01030300 - Mobiliario y Equipo de oficina | F183: DEN | G183: OFI311000 - Electrodoméstico | H183: E - Energía | I183: 50 - Otros | J183: ZMOB - Mobiliario | K183: 52141501 - Neveras para uso doméstico | L183: 6921 | M183: =+LEFT(D183,11) -> CMI01030300 | N183: =+LEFT(G183,9) -> OFI311000 | O183: =+LEFT(H183,1) -> E | P183: =+LEFT(I183,2) -> 50 | Q183: =+LEFT(J183,4) -> ZMOB | R183: =+LEFT(K183,8) -> 52141501
A184: 042409 | B184: MUEBLE:OFICINA | D184: CMI01030300 - Mobiliario y Equipo de oficina | F184: DEN | G184: MOB361000 - Mobiliario/Oficina | H184: E - Energía | I184: 50 - Otros | J184: ZMOB - Mobiliario | K184: 56101700 - Muebles de oficina | L184: 6922 | M184: =+LEFT(D184,11) -> CMI01030300 | N184: =+LEFT(G184,9) -> MOB361000 | O184: =+LEFT(H184,1) -> E | P184: =+LEFT(I184,2) -> 50 | Q184: =+LEFT(J184,4) -> ZMOB | R184: =+LEFT(K184,8) -> 56101700
A185: 042552 | B185: MESA:REUNIONES | D185: CMI01030300 - Mobiliario y Equipo de oficina | F185: DEN | G185: MOB361000 - Mobiliario/Oficina | H185: E - Energía | I185: 50 - Otros | J185: ZMOB - Mobiliario | K185: 56101706 - Mesas de conferencia | L185: 6923 | M185: =+LEFT(D185,11) -> CMI01030300 | N185: =+LEFT(G185,9) -> MOB361000 | O185: =+LEFT(H185,1) -> E | P185: =+LEFT(I185,2) -> 50 | Q185: =+LEFT(J185,4) -> ZMOB | R185: =+LEFT(K185,8) -> 56101706
A186: 042333 | B186: SILLA:GIRATORIA | D186: CMI01030300 - Mobiliario y Equipo de oficina | F186: DEN | G186: MOB361000 - Mobiliario/Oficina | H186: E - Energía | I186: 10 - Energía | J186: ZMOB - Mobiliario | K186: 56101504 - Asientos | L186: 6924 | M186: =+LEFT(D186,11) -> CMI01030300 | N186: =+LEFT(G186,9) -> MOB361000 | O186: =+LEFT(H186,1) -> E | P186: =+LEFT(I186,2) -> 10 | Q186: =+LEFT(J186,4) -> ZMOB | R186: =+LEFT(K186,8) -> 56101504
A187: 042505 | B187: SOFA | D187: CMI01030400 - Otro-Mobiliario | F187: DEN | G187: MOB361000 - Mobiliario/Oficina | H187: E - Energía | I187: 50 - Otros | J187: ZMOB - Mobiliario | K187: 56101502 - Sofás | L187: 6925 | M187: =+LEFT(D187,11) -> CMI01030400 | N187: =+LEFT(G187,9) -> MOB361000 | O187: =+LEFT(H187,1) -> E | P187: =+LEFT(I187,2) -> 50 | Q187: =+LEFT(J187,4) -> ZMOB | R187: =+LEFT(K187,8) -> 56101502
A188: 042344 | B188: SILLA:VISITANTES | D188: CMI01030300 - Mobiliario y Equipo de oficina | F188: DEN | G188: MOB361000 - Mobiliario/Oficina | H188: E - Energía | I188: 50 - Otros | J188: ZMOB - Mobiliario | K188: 56112103 - Sillas para visitantes | L188: 6926 | M188: =+LEFT(D188,11) -> CMI01030300 | N188: =+LEFT(G188,9) -> MOB361000 | O188: =+LEFT(H188,1) -> E | P188: =+LEFT(I188,2) -> 50 | Q188: =+LEFT(J188,4) -> ZMOB | R188: =+LEFT(K188,8) -> 56112103
A189: 042549 | B189: MESA:OFICINA | D189: CMI01030300 - Mobiliario y Equipo de oficina | F189: DEN | G189: MOB361000 - Mobiliario/Oficina | H189: E - Energía | I189: 50 - Otros | J189: ZMOB - Mobiliario | K189: 56101519 - Mesas | L189: 6927 | M189: =+LEFT(D189,11) -> CMI01030300 | N189: =+LEFT(G189,9) -> MOB361000 | O189: =+LEFT(H189,1) -> E | P189: =+LEFT(I189,2) -> 50 | Q189: =+LEFT(J189,4) -> ZMOB | R189: =+LEFT(K189,8) -> 56101519
A190: 086664 | B190: CONTENEDOR:CASA | D190: CMI02051300 - Otros-Mat de Construcción | F190: DEN | G190: MOB361000 - Mobiliario/Oficina | H190: E - Energía | I190: 50 - Otros | J190: ZMOB - Mobiliario | K190: 95131605 - Casa contenedor | L190: 6928 | M190: =+LEFT(D190,11) -> CMI02051300 | N190: =+LEFT(G190,9) -> MOB361000 | O190: =+LEFT(H190,1) -> E | P190: =+LEFT(I190,2) -> 50 | Q190: =+LEFT(J190,4) -> ZMOB | R190: =+LEFT(K190,8) -> 95131605
... A292: 010725 | B292: FILTRO:AGUA | D292: CMI02050100 - Accesorios | F292: DEN | G292: REP201100 - Rpto.Ind/Mecánicos | H292: E - Energía | I292: 50 - Otros | J292: ZRPI - Repuestos Industriales | K292: 40161502 - Filtros de agua | L292: 7030 | M292: =+LEFT(D292,11) -> CMI02050100 | N292: =+LEFT(G292,9) -> REP201100 | O292: =+LEFT(H292,1) -> E | P292: =+LEFT(I292,2) -> 50 | Q292: =+LEFT(J292,4) -> ZRPI | R292: =+LEFT(K292,8) -> 40161502
A293: 011378 | B293: VALVULA:BOLA | D293: CMI02200100 - Accesorios Hierro o Acero | E293: 6 | F293: DEN | G293: REP201100 - Rpto.Ind/Mecánicos | H293: E - Energía | I293: 50 - Otros | J293: ZRPI - Repuestos Industriales | K293: 40141607 - Válvulas de bola | L293: 7031 | M293: =+LEFT(D293,11) -> CMI02200100 | N293: =+LEFT(G293,9) -> REP201100 | O293: =+LEFT(H293,1) -> E | P293: =+LEFT(I293,2) -> 50 | Q293: =+LEFT(J293,4) -> ZRPI | R293: =+LEFT(K293,8) -> 40141607
A294: 011497 | B294: VALVULA REGULADORA | D294: CMI02090600 - Hidraulicos_Neumaticos | F294: DEN | G294: REP201100 - Rpto.Ind/Mecánicos | H294: E - Energía | I294: 50 - Otros | J294: ZRPI - Repuestos Industriales | K294: 40141654 - Válvula de regulación | L294: 7032 | M294: =+LEFT(D294,11) -> CMI02090600 | N294: =+LEFT(G294,9) -> REP201100 | O294: =+LEFT(H294,1) -> E | P294: =+LEFT(I294,2) -> 50 | Q294: =+LEFT(J294,4) -> ZRPI | R294: =+LEFT(K294,8) -> 40141654
A295: 011523 | B295: VALVULA:CHEQUE | D295: CMI02090600 - Hidraulicos_Neumaticos | F295: DEN | G295: REP201100 - Rpto.Ind/Mecánicos | H295: E - Energía | I295: 10 - Energía | J295: ZRPI - Repuestos Industriales | K295: 40141600 - Válvulas | L295: 7033 | M295: =+LEFT(D295,11) -> CMI02090600 | N295: =+LEFT(G295,9) -> REP201100 | O295: =+LEFT(H295,1) -> E | P295: =+LEFT(I295,2) -> 10 | Q295: =+LEFT(J295,4) -> ZRPI | R295: =+LEFT(K295,8) -> 40141600
A296: 013775 | B296: CUÑA | D296: CMI02090900 - Rep. Industriales-Mecánicos | F296: DEN | G296: REP201100 - Rpto.Ind/Mecánicos | H296: E - Energía | I296: 50 - Otros | J296: ZRPI - Repuestos Industriales | K296: 27112504 - Cuñas | L296: 7034 | M296: =+LEFT(D296,11) -> CMI02090900 | N296: =+LEFT(G296,9) -> REP201100 | O296: =+LEFT(H296,1) -> E | P296: =+LEFT(I296,2) -> 50 | Q296: =+LEFT(J296,4) -> ZRPI | R296: =+LEFT(K296,8) -> 27112504
A297: 014216 | B297: SOPORTE:INDUSTRIAL | D297: CMI02050100 - Accesorios | F297: DEN | G297: REP201100 - Rpto.Ind/Mecánicos | H297: E - Energía | I297: 50 - Otros | J297: ZRPI - Repuestos Industriales | K297: 31162500 - Soportes y puntales | L297: 7035 | M297: =+LEFT(D297,11) -> CMI02050100 | N297: =+LEFT(G297,9) -> REP201100 | O297: =+LEFT(H297,1) -> E | P297: =+LEFT(I297,2) -> 50 | Q297: =+LEFT(J297,4) -> ZRPI | R297: =+LEFT(K297,8) -> 31162500
A298: 014407 | B298: EMPAQUE | D298: CMI02090700 - Otros-Repuestos Industriales | F298: DEN | G298: REP201100 - Rpto.Ind/Mecánicos | H298: E - Energía | I298: 50 - Otros | J298: ZRPI - Repuestos Industriales | K298: 31400000 - Empaques | L298: 7036 | M298: =+LEFT(D298,11) -> CMI02090700 | N298: =+LEFT(G298,9) -> REP201100 | O298: =+LEFT(H298,1) -> E | P298: =+LEFT(I298,2) -> 50 | Q298: =+LEFT(J298,4) -> ZRPI | R298: =+LEFT(K298,8) -> 31400000
A299: 014653 | B299: JUNTA TORICA | D299: CMI02090900 - Rep. Industriales-Mecánicos | F299: DEN | G299: REP201100 - Rpto.Ind/Mecánicos | H299: E - Energía | I299: 50 - Otros | J299: ZRPI - Repuestos Industriales | K299: 31401503 - Empaque moldeado o – ring | L299: 7037 | M299: =+LEFT(D299,11) -> CMI02090900 | N299: =+LEFT(G299,9) -> REP201100 | O299: =+LEFT(H299,1) -> E | P299: =+LEFT(I299,2) -> 50 | Q299: =+LEFT(J299,4) -> ZRPI | R299: =+LEFT(K299,8) -> 31401503
A300: 014697 | B300: PASADOR:RETENCION | D300: CMI02090700 - Otros-Repuestos Industriales | F300: DEN | G300: REP201100 - Rpto.Ind/Mecánicos | H300: E - Energía | I300: 50 - Otros | J300: ZRPI - Repuestos Industriales | K300: 31163200 - Herraje de retención | L300: 7038 | M300: =+LEFT(D300,11) -> CMI02090700 | N300: =+LEFT(G300,9) -> REP201100 | O300: =+LEFT(H300,1) -> E | P300: =+LEFT(I300,2) -> 50 | Q300: =+LEFT(J300,4) -> ZRPI | R300: =+LEFT(K300,8) -> 31163200
A301: 015051 | B301: CUERPO:TENSOR | D301: CMI02090700 - Otros-Repuestos Industriales | F301: DEN | G301: REP201100 - Rpto.Ind/Mecánicos | H301: E - Energía | I301: 50 - Otros | J301: ZRPI - Repuestos Industriales | K301: 31162405 - Tensores | L301: 7039 | M301: =+LEFT(D301,11) -> CMI02090700 | N301: =+LEFT(G301,9) -> REP201100 | O301: =+LEFT(H301,1) -> E | P301: =+LEFT(I301,2) -> 50 | Q301: =+LEFT(J301,4) -> ZRPI | R301: =+LEFT(K301,8) -> 31162405
A302: 017202 | B302: PLACA DE PRUEBA | D302: CMI02090300 - Eléctricos | F302: DEN | G302: REP201100 - Rpto.Ind/Mecánicos | H302: E - Energía | I302: 50 - Otros | J302: ZRPI - Repuestos Industriales | K302: 32131000 - Acces mateprim pza compoelects | L302: 7040 | M302: =+LEFT(D302,11) -> CMI02090300 | N302: =+LEFT(G302,9) -> REP201100 | O302: =+LEFT(H302,1) -> E | P302: =+LEFT(I302,2) -> 50 | Q302: =+LEFT(J302,4) -> ZRPI | R302: =+LEFT(K302,8) -> 32131000
A303: 017374 | B303: INTERRUPTOR;CIRCUITO | D303: CMI02090300 - Eléctricos | F303: DEN | G303: REP201100 - Rpto.Ind/Mecánicos | H303: E - Energía | I303: 50 - Otros | J303: ZRPI - Repuestos Industriales | K303: 39121601 - Breakers de circuito | L303: 7041 | M303: =+LEFT(D303,11) -> CMI02090300 | N303: =+LEFT(G303,9) -> REP201100 | O303: =+LEFT(H303,1) -> E | P303: =+LEFT(I303,2) -> 50 | Q303: =+LEFT(J303,4) -> ZRPI | R303: =+LEFT(K303,8) -> 39121601
A304: 017409 | B304: BOBINA:ELECTRICIDAD | D304: CMI02090300 - Eléctricos | F304: DEN | G304: REP201100 - Rpto.Ind/Mecánicos | H304: E - Energía | I304: 50 - Otros | J304: ZRPI - Repuestos Industriales | K304: 39121010 - Bobinas magnéticas | L304: 7042 | M304: =+LEFT(D304,11) -> CMI02090300 | N304: =+LEFT(G304,9) -> REP201100 | O304: =+LEFT(H304,1) -> E | P304: =+LEFT(I304,2) -> 50 | Q304: =+LEFT(J304,4) -> ZRPI | R304: =+LEFT(K304,8) -> 39121010
A305: 017921 | B305: CONJUNTO AISLADORES | D305: CMI02051200 - Materiales Eléctricos | F305: DEN | G305: REP201100 - Rpto.Ind/Mecánicos | H305: E - Energía | I305: 50 - Otros | J305: ZRPI - Repuestos Industriales | K305: 39121721 - Aislantes eléctricos | L305: 7043 | M305: =+LEFT(D305,11) -> CMI02051200 | N305: =+LEFT(G305,9) -> REP201100 | O305: =+LEFT(H305,1) -> E | P305: =+LEFT(I305,2) -> 50 | Q305: =+LEFT(J305,4) -> ZRPI | R305: =+LEFT(K305,8) -> 39121721
... A354: 006400 | B354: CADENA:RODILLO | D354: CMI02090700 - Otros-Repuestos Industriales | F354: DEN | G354: REP201100 - Rpto.Ind/Mecánicos | H354: E - Energía | I354: 50 - Otros | J354: ZRPI - Repuestos Industriales | K354: 31151603 - Cadenas de rodillos | L354: 7092 | M354: =+LEFT(D354,11) -> CMI02090700 | N354: =+LEFT(G354,9) -> REP201100 | O354: =+LEFT(H354,1) -> E | P354: =+LEFT(I354,2) -> 50 | Q354: =+LEFT(J354,4) -> ZRPI | R354: =+LEFT(K354,8) -> 31151603
A355: 006436 | B355: ACOPLE:FLEXIBLE | D355: CMI02090700 - Otros-Repuestos Industriales | E355: 6 | F355: DEN | G355: REP201100 - Rpto.Ind/Mecánicos | H355: E - Energía | I355: 50 - Otros | J355: ZRPI - Repuestos Industriales | K355: 31163021 - Acople universal flexible | L355: 7093 | M355: =+LEFT(D355,11) -> CMI02090700 | N355: =+LEFT(G355,9) -> REP201100 | O355: =+LEFT(H355,1) -> E | P355: =+LEFT(I355,2) -> 50 | Q355: =+LEFT(J355,4) -> ZRPI | R355: =+LEFT(K355,8) -> 31163021
A356: 006558 | B356: ESLABON:CADENA | D356: CMI02090700 - Otros-Repuestos Industriales | F356: DEN | G356: REP201100 - Rpto.Ind/Mecánicos | H356: E - Energía | I356: 50 - Otros | J356: ZRPI - Repuestos Industriales | K356: 31151609 - Eslabones de cadena | L356: 7094 | M356: =+LEFT(D356,11) -> CMI02090700 | N356: =+LEFT(G356,9) -> REP201100 | O356: =+LEFT(H356,1) -> E | P356: =+LEFT(I356,2) -> 50 | Q356: =+LEFT(J356,4) -> ZRPI | R356: =+LEFT(K356,8) -> 31151609
A357: 006602 | B357: ANILLO:PISTON | D357: CMI02090700 - Otros-Repuestos Industriales | F357: DEN | G357: REP201100 - Rpto.Ind/Mecánicos | H357: E - Energía | I357: 50 - Otros | J357: ZRPI - Repuestos Industriales | K357: 26101727 - Anillo de pistón | L357: 7095 | M357: =+LEFT(D357,11) -> CMI02090700 | N357: =+LEFT(G357,9) -> REP201100 | O357: =+LEFT(H357,1) -> E | P357: =+LEFT(I357,2) -> 50 | Q357: =+LEFT(J357,4) -> ZRPI | R357: =+LEFT(K357,8) -> 26101727
A358: 006626 | B358: MANGA:TRANSMISION | D358: CMI02090700 - Otros-Repuestos Industriales | F358: DEN | G358: REP201100 - Rpto.Ind/Mecánicos | H358: E - Energía | I358: 50 - Otros | J358: ZRPI - Repuestos Industriales | K358: 26111531 - Manguitos de la transmisión | L358: 7096 | M358: =+LEFT(D358,11) -> CMI02090700 | N358: =+LEFT(G358,9) -> REP201100 | O358: =+LEFT(H358,1) -> E | P358: =+LEFT(I358,2) -> 50 | Q358: =+LEFT(J358,4) -> ZRPI | R358: =+LEFT(K358,8) -> 26111531
A359: 006664 | B359: RODAMIENTO BOLAS | D359: CMI02090700 - Otros-Repuestos Industriales | F359: DEN | G359: REP201100 - Rpto.Ind/Mecánicos | H359: E - Energía | I359: 50 - Otros | J359: ZRPI - Repuestos Industriales | K359: 31171504 - Rodamientos de balineras | L359: 7097 | M359: =+LEFT(D359,11) -> CMI02090700 | N359: =+LEFT(G359,9) -> REP201100 | O359: =+LEFT(H359,1) -> E | P359: =+LEFT(I359,2) -> 50 | Q359: =+LEFT(J359,4) -> ZRPI | R359: =+LEFT(K359,8) -> 31171504
A360: 006692 | B360: RODAMIENTO:CONICO | D360: CMI02090700 - Otros-Repuestos Industriales | F360: DEN | G360: REP201100 - Rpto.Ind/Mecánicos | H360: E - Energía | I360: 50 - Otros | J360: ZRPI - Repuestos Industriales | K360: 31171516 - Rodamientos cónicos | L360: 7098 | M360: =+LEFT(D360,11) -> CMI02090700 | N360: =+LEFT(G360,9) -> REP201100 | O360: =+LEFT(H360,1) -> E | P360: =+LEFT(I360,2) -> 50 | Q360: =+LEFT(J360,4) -> ZRPI | R360: =+LEFT(K360,8) -> 31171516
A361: 006715 | B361: RODAMIENTO:LINEAL | D361: CMI02090700 - Otros-Repuestos Industriales | F361: DEN | G361: REP201100 - Rpto.Ind/Mecánicos | H361: E - Energía | I361: 50 - Otros | J361: ZRPI - Repuestos Industriales | K361: 31171506 - Rodamientos lineales | L361: 7099 | M361: =+LEFT(D361,11) -> CMI02090700 | N361: =+LEFT(G361,9) -> REP201100 | O361: =+LEFT(H361,1) -> E | P361: =+LEFT(I361,2) -> 50 | Q361: =+LEFT(J361,4) -> ZRPI | R361: =+LEFT(K361,8) -> 31171506
A362: 006722 | B362: BUJE:MANGUITO | D362: CMI02090700 - Otros-Repuestos Industriales | F362: DEN | G362: REP201100 - Rpto.Ind/Mecánicos | H362: E - Energía | I362: 50 - Otros | J362: ZRPI - Repuestos Industriales | K362: 31171600 - Cojinetes | L362: 7100 | M362: =+LEFT(D362,11) -> CMI02090700 | N362: =+LEFT(G362,9) -> REP201100 | O362: =+LEFT(H362,1) -> E | P362: =+LEFT(I362,2) -> 50 | Q362: =+LEFT(J362,4) -> ZRPI | R362: =+LEFT(K362,8) -> 31171600
A363: 007822 | B363: GUIA | D363: CMI02090700 - Otros-Repuestos Industriales | F363: DEN | G363: REP201100 - Rpto.Ind/Mecánicos | H363: E - Energía | I363: 50 - Otros | J363: ZRPI - Repuestos Industriales | K363: 31171500 - Rodamientos | L363: 7101 | M363: =+LEFT(D363,11) -> CMI02090700 | N363: =+LEFT(G363,9) -> REP201100 | O363: =+LEFT(H363,1) -> E | P363: =+LEFT(I363,2) -> 50 | Q363: =+LEFT(J363,4) -> ZRPI | R363: =+LEFT(K363,8) -> 31171500
A364: 007994 | B364: SIERRA:DE CADENA | D364: CMI02090700 - Otros-Repuestos Industriales | F364: DEN | G364: REP201100 - Rpto.Ind/Mecánicos | H364: E - Energía | I364: 50 - Otros | J364: ZRPI - Repuestos Industriales | K364: 27112823 - Cadenas de corte | L364: 7102 | M364: =+LEFT(D364,11) -> CMI02090700 | N364: =+LEFT(G364,9) -> REP201100 | O364: =+LEFT(H364,1) -> E | P364: =+LEFT(I364,2) -> 50 | Q364: =+LEFT(J364,4) -> ZRPI | R364: =+LEFT(K364,8) -> 27112823
A365: 010126 | B365: FILTRO:FLUIDOS | D365: CMI02090700 - Otros-Repuestos Industriales | F365: DEN | G365: REP201100 - Rpto.Ind/Mecánicos | H365: E - Energía | I365: 50 - Otros | J365: ZRPI - Repuestos Industriales | K365: 40161500 - Filtros | L365: 7103 | M365: =+LEFT(D365,11) -> CMI02090700 | N365: =+LEFT(G365,9) -> REP201100 | O365: =+LEFT(H365,1) -> E | P365: =+LEFT(I365,2) -> 50 | Q365: =+LEFT(J365,4) -> ZRPI | R365: =+LEFT(K365,8) -> 40161500
A366: 010127 | B366: FILTRO:PRESION | D366: CMI02090700 - Otros-Repuestos Industriales | F366: DEN | G366: REP201100 - Rpto.Ind/Mecánicos | H366: E - Energía | I366: 50 - Otros | J366: ZRPI - Repuestos Industriales | K366: 40161500 - Filtros | L366: 7104 | M366: =+LEFT(D366,11) -> CMI02090700 | N366: =+LEFT(G366,9) -> REP201100 | O366: =+LEFT(H366,1) -> E | P366: =+LEFT(I366,2) -> 50 | Q366: =+LEFT(J366,4) -> ZRPI | R366: =+LEFT(K366,8) -> 40161500
...
